django_aggressivequery/__init__.py
django_aggressivequery/extensions.py
django_aggressivequery/extraction.py
django_aggressivequery/functional.py
django_aggressivequery/structures.py
django_aggressivequery-0.3.2.dist-info/DESCRIPTION.rst
django_aggressivequery-0.3.2.dist-info/entry_points.txt
django_aggressivequery-0.3.2.dist-info/METADATA
django_aggressivequery-0.3.2.dist-info/metadata.json
django_aggressivequery-0.3.2.dist-info/RECORD
django_aggressivequery-0.3.2.dist-info/top_level.txt
django_aggressivequery-0.3.2.dist-info/WHEEL
