Metadata-Version: 2.0
Name: django-aggressivequery
Version: 0.3.2
Summary: handling select_related and prefetch_reated, semi-automatically
Home-page: https://github.com/podhmo/django-aggressivequery
Author: podhmo
Author-email: UNKNOWN
License: UNKNOWN
Keywords: django restframework return_fields
Platform: UNKNOWN
Classifier: Programming Language :: Python
Classifier: Programming Language :: Python :: Implementation :: CPython
Classifier: Framework :: Django
Classifier: License :: OSI Approved :: BSD License
Requires-Dist: django
Provides-Extra: docs
Provides-Extra: testing
Requires-Dist: tox; extra == 'testing'
